linode_dyndns/__init__.py
linode_dyndns/__main__.py
linode_dyndns/version.py
linode_dyndns-1.3.0.dist-info/LICENSE
linode_dyndns-1.3.0.dist-info/METADATA
linode_dyndns-1.3.0.dist-info/WHEEL
linode_dyndns-1.3.0.dist-info/entry_points.txt
linode_dyndns-1.3.0.dist-info/top_level.txt
linode_dyndns-1.3.0.dist-info/RECORD
