Metadata-Version: 2.1
Name: linode-dyndns
Version: 1.3.0
Summary: A Python tool for dynamically updating Linode Domain Records
Author-email: Kyle Colantonio <k@yle.sh>
License: MIT
Keywords: automation,linode,dyndns,dns
Classifier: Development Status :: 5 - Production/Stable
Classifier: Intended Audience :: Developers
Classifier: Intended Audience :: Information Technology
Classifier: Intended Audience :: System Administrators
Classifier: License :: OSI Approved :: MIT License
Classifier: Operating System :: OS Independent
Classifier: Programming Language :: Python :: 3
Classifier: Topic :: Software Development :: Libraries :: Python Modules
Classifier: Topic :: System :: Systems Administration
Classifier: Topic :: Utilities
Requires-Python: >=3.9
License-File: LICENSE
Requires-Dist: click (>=8.1)
Requires-Dist: requests (>=2.28)
Requires-Dist: linode-api4 (>=5.3)
